bookstore/__init__.py
bookstore/_version.py
bookstore/archive.py
bookstore/bookstore_config.py
bookstore/clone.html
bookstore/clone.py
bookstore/handlers.py
bookstore/publish.py
bookstore/s3_paths.py
bookstore/utils.py
bookstore/client/__init__.py
bookstore/client/nb_client.py
bookstore/client/store_client.py
bookstore/tests/__init__.py
bookstore/tests/test_archive.py
bookstore/tests/test_bookstore_config.py
bookstore/tests/test_clone.py
bookstore/tests/test_handlers.py
bookstore/tests/test_publish.py
bookstore/tests/test_s3_paths.py
bookstore/tests/test_utils.py
bookstore/tests/test_version.py
bookstore/tests/client/__init__.py
bookstore/tests/client/client_fixtures.py
bookstore/tests/client/test_nb_client.py
bookstore/tests/test_files/EmptyNotebook.ipynb
bookstore-2.5.1.data/data/etc/jupyter/jupyter_notebook_config.d/bookstore.json
bookstore-2.5.1.dist-info/METADATA
bookstore-2.5.1.dist-info/RECORD
bookstore-2.5.1.dist-info/WHEEL
bookstore-2.5.1.dist-info/top_level.txt
