Metadata-Version: 2.1
Name: bookstore
Version: 2.5.1
Summary: Storage Workflows for Notebooks
Home-page: https://github.com/nteract/bookstore
Author: nteract contributors
Author-email: nteract@googlegroups.com
License: BSD
Project-URL: Documentation, https://bookstore.readthedocs.io
Project-URL: Funding, https://nteract.io
Project-URL: Source, https://github.com/nteract/bookstore/
Project-URL: Tracker, https://github.com/nteract/bookstore/issues
Keywords: jupyter storage nteract notebook
Platform: UNKNOWN
Classifier: Development Status :: 4 - Beta
Classifier: Intended Audience :: Developers
Classifier: Intended Audience :: System Administrators
Classifier: Intended Audience :: Science/Research
Classifier: License :: OSI Approved :: BSD License
Classifier: Programming Language :: Python
Classifier: Programming Language :: Python :: 3
Provides-Extra: docs
Provides-Extra: test
